{"is_source_file": true, "format": "JavaScript (ES Module)", "description": "ESLint configuration file written in JavaScript, configuring compatibility extensions for ESLint in a Next.js project.", "external_files": ["@eslint/eslintrc", "path", "url"], "external_methods": ["dirname", "fileURLToPath", "compat.extends"], "published": ["default"], "classes": [], "methods": [{"name": "compat.extends", "description": "Extends ESLint configuration with specified preset configurations."}], "calls": ["compat.extends"], "search-terms": ["eslint", "ESLint configuration", "Next.js", "typescript", "compat", "extending ESLint configs"], "state": 2, "file_id": 9, "knowledge_revision": 16, "git_revision": "5a8a044309d75e2a59baa709fa390ce0a3939b9c", "hash": "b43f470c5df5e9ff4c2f5e0bd917a881", "format-version": 4, "code-base-name": "tic_tac_toe_frontend", "filename": "tic_tac_toe_frontend/eslint.config.mjs", "revision_history": [{"16": "5a8a044309d75e2a59baa709fa390ce0a3939b9c"}]}